[
  {
    "productId": "4e8343d7-8dbe-408f-bd82-3732d6c3793d",
    "optionName": "quality",
    "optionValues": ["720p", "1080p", "4k"]
  },
  {
    "productId": "4e8343d7-8dbe-408f-bd82-3732d6c3793d",
    "optionName": "language",
    "optionValues": ["english", "spanish", "french"]
  },
  {
    "productId": "512af1f2-acc0-4464-a6fb-71236b12ff43",
    "optionName": "format",
    "optionValues": ["DVD", "Blu-ray", "Digital"]
  },
  {
    "productId": "f88769c0-ee7c-4b9a-aa6e-63b45657328b",
    "optionName": "language",
    "optionValues": ["English", "Spanish"]
  },
  {
    "productId": "04906a83-7e6e-4066-92f4-1caff5857fec",
    "optionName": "quality",
    "optionValues": ["720p", "1080p"]
  },
  {
    "productId": "f0c8198b-59d1-4a5a-a577-e9aee3d01946",
    "optionName": "region",
    "optionValues": ["Region 1", "Region 2", "Region 3"]
  },
  {
    "productId": "322ffabc-66dc-4deb-9821-ac4c2cbabb90",
    "optionName": "edition",
    "optionValues": ["Standard", "Collector's"]
  },
  {
    "productId": "f69cb1ea-c238-413a-9fd7-75138fcf8a78",
    "optionName": "language",
    "optionValues": ["English", "French"]
  },
  {
    "productId": "5fd35dfd-19be-4371-a590-ea1418a975d3",
    "optionName": "quality",
    "optionValues": ["HD", "4K"]
  },
  {
    "productId": "3ff6650b-cbbd-409f-95dd-634d86e84bf0",
    "optionName": "format",
    "optionValues": ["Digital", "Blu-ray"]
  },
  {
    "productId": "4e78fff8-84f3-49ae-bd4c-039d1e220e68",
    "optionName": "region",
    "optionValues": ["Region A", "Region B"]
  },
  {
    "productId": "8717d659-7ecf-4873-98b5-b4e0d3a6cca4",
    "optionName": "language",
    "optionValues": ["English", "German"]
  }
  ,
  { "productId": "14a19864-0a6e-4763-a0f7-480136a597be", "optionName": "format", "optionValues": ["Digital", "Blu-ray"] },
  { "productId": "c9c4fb20-8a05-4e3c-8c56-9abef9f3882b", "optionName": "quality", "optionValues": ["HD", "4K"] },
  { "productId": "cfc846c2-ec59-4860-9fde-6199885fa962", "optionName": "language", "optionValues": ["English", "Spanish"] },
  { "productId": "9d85a63e-b08d-4e75-9f52-9255bb0436dc", "optionName": "region", "optionValues": ["Region 1", "Region 2"] },
  { "productId": "3a3f8f81-78a4-4aee-86a9-460979714610", "optionName": "edition", "optionValues": ["Standard", "Deluxe"] },
  { "productId": "c0c6d334-bcc8-4237-bc34-03afff15dacf", "optionName": "quality", "optionValues": ["720p", "1080p"] },
  { "productId": "98ec1b8a-67bf-41c3-81f9-9ddb950f46df", "optionName": "format", "optionValues": ["Digital"] },
  { "productId": "f3e9d2be-33d4-4a3d-97c9-c3d6869284ce", "optionName": "language", "optionValues": ["English", "French"] },
  { "productId": "6acc96c4-bd15-479d-8b64-7433717369dd", "optionName": "region", "optionValues": ["Region 1", "Region 3"] },
  { "productId": "48ba8fc7-9cd2-4285-a710-55d92005e13c", "optionName": "quality", "optionValues": ["HD", "4K"] },
  { "productId": "ec332d32-df59-4615-90d0-a81142bfa652", "optionName": "format", "optionValues": ["Blu-ray", "Digital"] },
  { "productId": "1f6e91d8-c180-4347-b88e-9d2686fffe24", "optionName": "edition", "optionValues": ["Standard"] },
  { "productId": "d8667afe-bd9f-4cf9-9281-c0e5b25e5e25", "optionName": "language", "optionValues": ["English"] },
  { "productId": "9a1b5673-b102-48f7-a45d-95eed3333045", "optionName": "region", "optionValues": ["Region 2"] },
  { "productId": "61b2d5bb-f8c9-471c-ae5e-acd09ce472be", "optionName": "quality", "optionValues": ["720p"] },
  { "productId": "ac98592f-f9b7-4d3d-990e-580681ebe618", "optionName": "format", "optionValues": ["Digital"] },
  { "productId": "09a0e9f4-a210-4ed9-b619-a8d5df539c9e", "optionName": "edition", "optionValues": ["Collector's"] },
  { "productId": "a8e9da1a-82fc-4355-bfb2-a141722169db", "optionName": "language", "optionValues": ["English"] },
  { "productId": "54d88f76-938d-49cf-a10e-10286a598f9d", "optionName": "region", "optionValues": ["Region 1"] },
  { "productId": "d6ec996b-5cd4-490c-97ea-bb2465d5140e", "optionName": "quality", "optionValues": ["HD"] },
  { "productId": "5e7e489e-554c-425b-bad4-1754e7040b5f", "optionName": "format", "optionValues": ["Blu-ray"] },
  { "productId": "da5eb0ca-d93a-4ae2-9f5d-5f5edd1b1c97", "optionName": "edition", "optionValues": ["Standard"] },
  { "productId": "f115671c-c521-45d6-8bf1-27d9159f1a98", "optionName": "language", "optionValues": ["French"] },
  { "productId": "489053b9-e280-4719-b403-78d83bfb6473", "optionName": "region", "optionValues": ["Region 2"] },
  { "productId": "9ab0cc25-b823-43e9-b6b7-28cdf4cf3145", "optionName": "platform", "optionValues": ["PC", "Console"] },
  { "productId": "5ca4d745-151f-48b6-b88e-42df634cb95a", "optionName": "platform", "optionValues": ["PC", "Console"] },
  { "productId": "e1a2b3c4-d5e6-7f89-0a1b-2c3d4e5f6g7h", "optionName": "format", "optionValues": ["PDF", "ePub"] },
  { "productId": "f1g2h3i4-j5k6-l7m8-n9o0-p1q2r3s4t5u6", "optionName": "quality", "optionValues": ["MP3", "FLAC"] },
  { "productId": "v1w2x3y4-z5a6-b7c8-d9e0-f1g2h3i4j5k6", "optionName": "platform", "optionValues": ["Windows", "Mac"] },
  { "productId": "l1m2n3o4-p5q6-r7s8-t9u0-v1w2x3y4z5a6", "optionName": "region", "optionValues": ["Region 1"] },
  { "productId": "b1c2d3e4-f5g6-h7i8-j9k0-l1m2n3o4p5q6", "optionName": "language", "optionValues": ["English"] },
  { "productId": "r1s2t3u4-v5w6-x7y8-z9a0-b1c2d3e4f5g6", "optionName": "quality", "optionValues": ["HD"] },
  { "productId": "h1i2j3k4-l5m6-n7o8-p9q0-r1s2t3u4v5w6", "optionName": "format", "optionValues": ["Digital"] },
  { "productId": "x1y2z3a4-b5c6-d7e8-f9g0-h1i2j3k4l5m6", "optionName": "edition", "optionValues": ["Standard"] }
]